DESCRIPTION.rst
MANIFEST.in
README.rst
setup.cfg
setup.py
dataq/__init__.py
dataq/actions.py
dataq/dataq_cli.py
dataq/dataq_pop_svc.py
dataq/dataq_push_svc.py
dataq/dbvars.py
dataq/dqutils.py
dataq/file_type.py
dataq/loggingCfg.py
dataq/test_feeder.py
dataq.egg-info/PKG-INFO
dataq.egg-info/SOURCES.txt
dataq.egg-info/dependency_links.txt
dataq.egg-info/entry_points.txt
dataq.egg-info/requires.txt
dataq.egg-info/top_level.txt