Metadata-Version: 1.1
Name: dataq
Version: 0.0.dev5
Summary: Manage data-queue with associated Action on pop
Home-page: https://github.com/pothiers/dataq
Author: The Python Packaging Authority
Author-email: pypa-dev@googlegroups.com
License: MIT
Keywords: networked queue management data-flow
Platform: UNKNOWN
Classifier: Development Status :: 3 - Alpha
Classifier: Intended Audience :: Information Technology
Classifier: Intended Audience :: Science/Research
Classifier: Intended Audience :: System Administrators
Classifier: Intended Audience :: Telecommunications Industry
Classifier: Topic :: Scientific/Engineering :: Astronomy
Classifier: License :: OSI Approved :: MIT License
Classifier: Programming Language :: Python :: 3.3
Classifier: Programming Language :: Python :: 3.4
